{
  "items": [
    {
      "iname": "GM_0001",
      "grpID": "GMG_NORMAL",
      "condition": {
        "type": 3,
        "ival": 10
      },
      "rewards": [
        {
          "type": 1,
          "iname": "GE_REWARD1",
          "num": 1
        }
      ]
    },
    {
      "iname": "GM_0002",
      "grpID": "GMG_NORMAL",
      "condition": {
        "type": 2,
        "ival": 1
      },
      "rewards": [
        {
          "type": 1,
          "iname": "GE_REWARD2",
          "num": 1
        }
      ]
    },
    {
      "iname": "GM_0003",
      "grpID": "GMG_NORMAL",
      "condition": {
        "type": 3,
        "ival": 15
      },
      "rewards": [
        {
          "type": 1,
          "iname": "GE_REWARD3",
          "num": 1
        }
      ]
    },
    {
      "iname": "GM_0004",
      "grpID": "GMG_NORMAL",
      "condition": {
        "type": 2,
        "ival": 2
      },
      "rewards": [
        {
          "type": 1,
          "iname": "GE_REWARD4",
          "num": 1
        }
      ]
    },
    {
      "iname": "GM_0005",
      "grpID": "GMG_NORMAL",
      "condition": {
        "type": 3,
        "ival": 20
      },
      "rewards": [
        {
          "type": 1,
          "iname": "GE_REWARD5",
          "num": 1
        }
      ]
    },
    {
      "iname": "GM_0006",
      "grpID": "GMG_NORMAL",
      "condition": {
        "type": 8,
        "sval": [
          "GSI_LION"
        ],
        "ival": 2
      },
      "rewards": [
        {
          "type": 1,
          "iname": "GE_REWARD6",
          "num": 1
        }
      ]
    },
    {
      "iname": "GM_0007",
      "grpID": "GMG_NORMAL",
      "condition": {
        "type": 9,
        "ival": 100
      },
      "rewards": [
        {
          "type": 1,
          "iname": "GE_REWARD7",
          "num": 1
        }
      ]
    },
    {
      "iname": "GM_0008",
      "grpID": "GMG_NORMAL",
      "condition": {
        "type": 7,
        "ival": 5000000
      },
      "rewards": [
        {
          "type": 1,
          "iname": "GE_REWARD8",
          "num": 1
        }
      ]
    },
    {
      "iname": "GM_0009",
      "grpID": "GMG_NORMAL",
      "condition": {
        "type": 10,
        "ival": 1
      },
      "rewards": [
        {
          "type": 1,
          "iname": "GE_REWARD9",
          "num": 1
        }
      ]
    },
    {
      "iname": "GM_0010",
      "grpID": "GMG_NORMAL",
      "condition": {
        "type": 6,
        "sval": [
          "IT_EC_GUILD"
        ],
        "ival": 10000
      },
      "rewards": [
        {
          "type": 1,
          "iname": "GE_REWARD10",
          "num": 1
        }
      ]
    },
    {
      "iname": "GM_0011",
      "grpID": "GMG_NORMAL",
      "condition": {
        "type": 6,
        "sval": [
          "IT_EC_GUILD"
        ],
        "ival": 100000
      },
      "rewards": [
        {
          "type": 1,
          "iname": "GE_REWARD11",
          "num": 1
        }
      ]
    },
    {
      "iname": "GM_0012",
      "grpID": "GMG_NORMAL",
      "condition": {
        "type": 11,
        "sval": [
          "GL_CHAMPION3"
        ],
        "ival": 1
      },
      "rewards": [
        {
          "type": 1,
          "iname": "GE_REWARD12",
          "num": 1
        }
      ]
    },
    {
      "iname": "GM_0013",
      "grpID": "GMG_NORMAL",
      "condition": {
        "type": 11,
        "sval": [
          "GL_DIA3"
        ],
        "ival": 1
      },
      "rewards": [
        {
          "type": 1,
          "iname": "GE_REWARD13",
          "num": 1
        }
      ]
    },
    {
      "iname": "GM_0014",
      "grpID": "GMG_NORMAL",
      "condition": {
        "type": 11,
        "sval": [
          "GL_GOLD3"
        ],
        "ival": 1
      },
      "rewards": [
        {
          "type": 1,
          "iname": "GE_REWARD14",
          "num": 1
        }
      ]
    },
    {
      "iname": "GM_0015",
      "grpID": "GMG_NORMAL",
      "condition": {
        "type": 11,
        "sval": [
          "GL_SILVER3"
        ],
        "ival": 1
      },
      "rewards": [
        {
          "type": 1,
          "iname": "GE_REWARD15",
          "num": 1
        }
      ]
    }
  ]
}