{
  "items": [
    {
      "iname": "JB_FF10_TIDU_M",
      "lv": {
        "unit": 99,
        "m": 15,
        "s1": 15,
        "s2": 15
      },
      "material_item_id": "JBEX_WATER_UR"
    },
    {
      "iname": "JB_FF10_YUNA_M",
      "lv": {
        "unit": 99,
        "m": 15,
        "s1": 15,
        "s2": 15
      },
      "material_item_id": "JBEX_SHINE_UR"
    },
    {
      "iname": "JB_LW_MONT_M",
      "lv": {
        "unit": 99,
        "m": 15,
        "s1": 15,
        "s2": 15
      },
      "material_item_id": "JBEX_SOIL_SSR"
    },
    {
      "iname": "JB_LW_ROBB_M",
      "lv": {
        "unit": 99,
        "m": 15,
        "s1": 15,
        "s2": 15
      },
      "material_item_id": "JBEX_SHINE_UR"
    },
    {
      "iname": "JB_LW_ELDE_M",
      "lv": {
        "unit": 99,
        "m": 15,
        "s1": 15,
        "s2": 15
      },
      "material_item_id": "JBEX_FIRE_UR"
    },
    {
      "iname": "JB_LW_STRN_M",
      "lv": {
        "unit": 99,
        "m": 15,
        "s1": 15,
        "s2": 15
      },
      "material_item_id": "JBEX_DARK_UR"
    },
    {
      "iname": "JB_LW_ORDR_M",
      "lv": {
        "unit": 99,
        "m": 15,
        "s1": 15,
        "s2": 15
      },
      "material_item_id": "JBEX_WIND_UR"
    },
    {
      "iname": "JB_LW_BYLO_M",
      "lv": {
        "unit": 99,
        "m": 15,
        "s1": 15,
        "s2": 15
      },
      "material_item_id": "JBEX_SOIL_SR"
    },
    {
      "iname": "JB_LW_RART_M",
      "lv": {
        "unit": 99,
        "m": 15,
        "s1": 15,
        "s2": 15
      },
      "material_item_id": "JBEX_THUN_R"
    },
    {
      "iname": "JB_FF10_ARON_M",
      "lv": {
        "unit": 99,
        "m": 15,
        "s1": 15,
        "s2": 15
      },
      "material_item_id": "JBEX_ICE_UR"
    },
    {
      "iname": "JB_LW_ZIZA_M",
      "lv": {
        "unit": 99,
        "m": 15,
        "s1": 15,
        "s2": 15
      },
      "material_item_id": "JBEX_DARK_UR"
    },
    {
      "iname": "JB_LW_AILN_M",
      "lv": {
        "unit": 99,
        "m": 15,
        "s1": 15,
        "s2": 15
      },
      "material_item_id": "JBEX_SOIL_UR"
    },
    {
      "iname": "JB_LW_GLMS_M",
      "lv": {
        "unit": 99,
        "m": 15,
        "s1": 15,
        "s2": 15
      },
      "material_item_id": "JBEX_ICE_UR"
    },
    {
      "iname": "JB_LW_ZZAN_M",
      "lv": {
        "unit": 99,
        "m": 15,
        "s1": 15,
        "s2": 15
      },
      "material_item_id": "JBEX_WATER_N"
    },
    {
      "iname": "JB_LW_MDNA_M",
      "lv": {
        "unit": 99,
        "m": 15,
        "s1": 15,
        "s2": 15
      },
      "material_item_id": "JBEX_ICE_UR"
    },
    {
      "iname": "JB_LW_OOOO_M",
      "lv": {
        "unit": 99,
        "m": 15,
        "s1": 15,
        "s2": 15
      },
      "material_item_id": "JBEX_THUN_SSR"
    },
    {
      "iname": "JB_LW_PHBE_M",
      "lv": {
        "unit": 99,
        "m": 15,
        "s1": 15,
        "s2": 15
      },
      "material_item_id": "JBEX_SHINE_SR"
    },
    {
      "iname": "JB_NIER_N2TB_M",
      "lv": {
        "unit": 99,
        "m": 15,
        "s1": 15,
        "s2": 15
      },
      "material_item_id": "JBEX_WIND_UR"
    },
    {
      "iname": "JB_NIER_N9TS_M",
      "lv": {
        "unit": 99,
        "m": 15,
        "s1": 15,
        "s2": 15
      },
      "material_item_id": "JBEX_THUN_UR"
    },
    {
      "iname": "JB_LW_SIMR_M",
      "lv": {
        "unit": 99,
        "m": 15,
        "s1": 15,
        "s2": 15
      },
      "material_item_id": "JBEX_FIRE_SSR"
    },
    {
      "iname": "JB_LW_MONT_01_M",
      "lv": {
        "unit": 99,
        "m": 15,
        "s1": 15,
        "s2": 15
      },
      "material_item_id": "JBEX_FIRE_UR"
    },
    {
      "iname": "JB_LW_YERM_M",
      "lv": {
        "unit": 99,
        "m": 15,
        "s1": 15,
        "s2": 15
      },
      "material_item_id": "JBEX_WIND_UR"
    },
    {
      "iname": "JB_LW_NASR_M",
      "lv": {
        "unit": 99,
        "m": 15,
        "s1": 15,
        "s2": 15
      },
      "material_item_id": "JBEX_ICE_SSR"
    },
    {
      "iname": "JB_LW_ETRE_M",
      "lv": {
        "unit": 99,
        "m": 15,
        "s1": 15,
        "s2": 15
      },
      "material_item_id": "JBEX_SOIL_SSR"
    },
    {
      "iname": "JB_LW_RYEL_M",
      "lv": {
        "unit": 99,
        "m": 15,
        "s1": 15,
        "s2": 15
      },
      "material_item_id": "JBEX_SOIL_UR"
    },
    {
      "iname": "JB_LW_SIRM_M",
      "lv": {
        "unit": 99,
        "m": 15,
        "s1": 15,
        "s2": 15
      },
      "material_item_id": "JBEX_THUN_SSR"
    },
    {
      "iname": "JB_LW_RAIN_M",
      "lv": {
        "unit": 99,
        "m": 15,
        "s1": 15,
        "s2": 15
      },
      "material_item_id": "JBEX_FIRE_UR"
    },
    {
      "iname": "JB_LW_LSWL_M",
      "lv": {
        "unit": 99,
        "m": 15,
        "s1": 15,
        "s2": 15
      },
      "material_item_id": "JBEX_ICE_UR"
    },
    {
      "iname": "JB_LW_FDRC_M",
      "lv": {
        "unit": 99,
        "m": 15,
        "s1": 15,
        "s2": 15
      },
      "material_item_id": "JBEX_THUN_UR"
    },
    {
      "iname": "JB_LW_AYKA_M",
      "lv": {
        "unit": 99,
        "m": 15,
        "s1": 15,
        "s2": 15
      },
      "material_item_id": "JBEX_WIND_UR"
    },
    {
      "iname": "JB_LW_MURM_M",
      "lv": {
        "unit": 99,
        "m": 15,
        "s1": 15,
        "s2": 15
      },
      "material_item_id": "JBEX_SOIL_SR"
    },
    {
      "iname": "JB_LW_HLNA_01_M",
      "lv": {
        "unit": 99,
        "m": 15,
        "s1": 15,
        "s2": 15
      },
      "material_item_id": "JBEX_DARK_UR"
    },
    {
      "iname": "JB_LW_SDLX_M",
      "lv": {
        "unit": 99,
        "m": 15,
        "s1": 15,
        "s2": 15
      },
      "material_item_id": "JBEX_DARK_SSR"
    },
    {
      "iname": "JB_LW_VNLA_M",
      "lv": {
        "unit": 99,
        "m": 15,
        "s1": 15,
        "s2": 15
      },
      "material_item_id": "JBEX_DARK_UR"
    },
    {
      "iname": "JB_LW_DRIO_M",
      "lv": {
        "unit": 99,
        "m": 15,
        "s1": 15,
        "s2": 15
      },
      "material_item_id": "JBEX_WIND_SSR"
    },
    {
      "iname": "JB_LW_UNII_M",
      "lv": {
        "unit": 99,
        "m": 15,
        "s1": 15,
        "s2": 15
      },
      "material_item_id": "JBEX_WATER_SR"
    },
    {
      "iname": "JB_LW_MACR_M",
      "lv": {
        "unit": 99,
        "m": 15,
        "s1": 15,
        "s2": 15
      },
      "material_item_id": "JBEX_SHINE_UR"
    },
    {
      "iname": "JB_LW_RAMD_M",
      "lv": {
        "unit": 99,
        "m": 15,
        "s1": 15,
        "s2": 15
      },
      "material_item_id": "JBEX_WATER_SSR"
    },
    {
      "iname": "JB_LW_MICE_M",
      "lv": {
        "unit": 99,
        "m": 15,
        "s1": 15,
        "s2": 15
      },
      "material_item_id": "JBEX_FIRE_R"
    },
    {
      "iname": "JB_LW_THLA_01_M",
      "lv": {
        "unit": 99,
        "m": 15,
        "s1": 15,
        "s2": 15
      },
      "material_item_id": "JBEX_ICE_UR"
    },
    {
      "iname": "JB_FF1_WROL_M",
      "lv": {
        "unit": 99,
        "m": 15,
        "s1": 15,
        "s2": 15
      },
      "material_item_id": "JBEX_SHINE_UR"
    },
    {
      "iname": "JB_LW_CMLO_M",
      "lv": {
        "unit": 99,
        "m": 15,
        "s1": 15,
        "s2": 15
      },
      "material_item_id": "JBEX_SHINE_UR"
    },
    {
      "iname": "JB_LW_SZRT_M",
      "lv": {
        "unit": 99,
        "m": 15,
        "s1": 15,
        "s2": 15
      },
      "material_item_id": "JBEX_THUN_SSR"
    },
    {
      "iname": "JB_LW_DRND_M",
      "lv": {
        "unit": 99,
        "m": 15,
        "s1": 15,
        "s2": 15
      },
      "material_item_id": "JBEX_SOIL_SSR"
    },
    {
      "iname": "JB_LW_ZZAN_01_M",
      "lv": {
        "unit": 99,
        "m": 15,
        "s1": 15,
        "s2": 15
      },
      "material_item_id": "JBEX_SOIL_UR"
    },
    {
      "iname": "JB_LW_DEAN_M",
      "lv": {
        "unit": 99,
        "m": 15,
        "s1": 15,
        "s2": 15
      },
      "material_item_id": "JBEX_DARK_UR"
    },
    {
      "iname": "JB_LW_KTON_M",
      "lv": {
        "unit": 99,
        "m": 15,
        "s1": 15,
        "s2": 15
      },
      "material_item_id": "JBEX_SOIL_UR"
    },
    {
      "iname": "JB_LW_FRVA_M",
      "lv": {
        "unit": 99,
        "m": 15,
        "s1": 15,
        "s2": 15
      },
      "material_item_id": "JBEX_ICE_UR"
    },
    {
      "iname": "JB_LW_WHIS_M",
      "lv": {
        "unit": 99,
        "m": 15,
        "s1": 15,
        "s2": 15
      },
      "material_item_id": "JBEX_DARK_UR"
    },
    {
      "iname": "JB_LW_CLEY_M",
      "lv": {
        "unit": 99,
        "m": 15,
        "s1": 15,
        "s2": 15
      },
      "material_item_id": "JBEX_ICE_SSR"
    },
    {
      "iname": "JB_LW_SEVR_M",
      "lv": {
        "unit": 99,
        "m": 15,
        "s1": 15,
        "s2": 15
      },
      "material_item_id": "JBEX_WATER_SR"
    },
    {
      "iname": "JB_LW_MORE_M",
      "lv": {
        "unit": 99,
        "m": 15,
        "s1": 15,
        "s2": 15
      },
      "material_item_id": "JBEX_WATER_UR"
    },
    {
      "iname": "JB_LW_CWEL_M",
      "lv": {
        "unit": 99,
        "m": 15,
        "s1": 15,
        "s2": 15
      },
      "material_item_id": "JBEX_WIND_UR"
    },
    {
      "iname": "JB_LW_VSTR_M",
      "lv": {
        "unit": 99,
        "m": 15,
        "s1": 15,
        "s2": 15
      },
      "material_item_id": "JBEX_SHINE_SSR"
    },
    {
      "iname": "JB_LW_MURG_M",
      "lv": {
        "unit": 99,
        "m": 15,
        "s1": 15,
        "s2": 15
      },
      "material_item_id": "JBEX_SOIL_UR"
    },
    {
      "iname": "JB_LW_CRLT_M",
      "lv": {
        "unit": 99,
        "m": 15,
        "s1": 15,
        "s2": 15
      },
      "material_item_id": "JBEX_THUN_UR"
    },
    {
      "iname": "JB_LW_LILS_01_M",
      "lv": {
        "unit": 99,
        "m": 15,
        "s1": 15,
        "s2": 15
      },
      "material_item_id": "JBEX_SOIL_UR"
    },
    {
      "iname": "JB_LW_KTON_01_M",
      "lv": {
        "unit": 99,
        "m": 15,
        "s1": 15,
        "s2": 15
      },
      "material_item_id": "JBEX_FIRE_UR"
    },
    {
      "iname": "JB_LW_MRLK_M",
      "lv": {
        "unit": 99,
        "m": 15,
        "s1": 15,
        "s2": 15
      },
      "material_item_id": "JBEX_THUN_SSR"
    },
    {
      "iname": "JB_LW_RYER_M",
      "lv": {
        "unit": 99,
        "m": 15,
        "s1": 15,
        "s2": 15
      },
      "material_item_id": "JBEX_DARK_SR"
    },
    {
      "iname": "JB_LW_VLRC_M",
      "lv": {
        "unit": 99,
        "m": 15,
        "s1": 15,
        "s2": 15
      },
      "material_item_id": "JBEX_ICE_UR"
    },
    {
      "iname": "JB_LW_QILF_01_M",
      "lv": {
        "unit": 99,
        "m": 15,
        "s1": 15,
        "s2": 15
      },
      "material_item_id": "JBEX_SHINE_UR"
    },
    {
      "iname": "JB_LW_ELSR_01_M",
      "lv": {
        "unit": 99,
        "m": 15,
        "s1": 15,
        "s2": 15
      },
      "material_item_id": "JBEX_WATER_UR"
    },
    {
      "iname": "JB_LW_LMRE_M",
      "lv": {
        "unit": 99,
        "m": 15,
        "s1": 15,
        "s2": 15
      },
      "material_item_id": "JBEX_DARK_UR"
    },
    {
      "iname": "JB_LW_GRGS_M",
      "lv": {
        "unit": 99,
        "m": 15,
        "s1": 15,
        "s2": 15
      },
      "material_item_id": "JBEX_WIND_UR"
    },
    {
      "iname": "JB_FF7_CLUD_M",
      "lv": {
        "unit": 99,
        "m": 15,
        "s1": 15,
        "s2": 15
      },
      "material_item_id": "JBEX_THUN_UR"
    },
    {
      "iname": "JB_FF7_TIFA_M",
      "lv": {
        "unit": 99,
        "m": 15,
        "s1": 15,
        "s2": 15
      },
      "material_item_id": "JBEX_WIND_UR"
    },
    {
      "iname": "JB_FF7_AERT_M",
      "lv": {
        "unit": 99,
        "m": 15,
        "s1": 15,
        "s2": 15
      },
      "material_item_id": "JBEX_WATER_UR"
    },
    {
      "iname": "JB_FF7_BART_M",
      "lv": {
        "unit": 99,
        "m": 15,
        "s1": 15,
        "s2": 15
      },
      "material_item_id": "JBEX_ICE_UR"
    },
    {
      "iname": "JB_LW_ENBT_M",
      "lv": {
        "unit": 99,
        "m": 15,
        "s1": 15,
        "s2": 15
      },
      "material_item_id": "JBEX_SHINE_UR"
    },
    {
      "iname": "JB_LW_FINA_M",
      "lv": {
        "unit": 99,
        "m": 15,
        "s1": 15,
        "s2": 15
      },
      "material_item_id": "JBEX_SHINE_SSR"
    },
    {
      "iname": "JB_LW_SRJS_M",
      "lv": {
        "unit": 99,
        "m": 15,
        "s1": 15,
        "s2": 15
      },
      "material_item_id": "JBEX_ICE_SR"
    },
    {
      "iname": "JB_LW_GRSR_01_M",
      "lv": {
        "unit": 99,
        "m": 15,
        "s1": 15,
        "s2": 15
      },
      "material_item_id": "JBEX_FIRE_UR"
    },
    {
      "iname": "JB_TOMB_LARA_M",
      "lv": {
        "unit": 99,
        "m": 15,
        "s1": 15,
        "s2": 15
      },
      "material_item_id": "JBEX_WATER_UR"
    },
    {
      "iname": "JB_LW_VNLA_01_M",
      "lv": {
        "unit": 99,
        "m": 15,
        "s1": 15,
        "s2": 15
      },
      "material_item_id": "JBEX_SOIL_UR"
    },
    {
      "iname": "JB_LW_RAMD_01_M",
      "lv": {
        "unit": 99,
        "m": 15,
        "s1": 15,
        "s2": 15
      },
      "material_item_id": "JBEX_WATER_UR"
    },
    {
      "iname": "JB_LW_MACR_01_M",
      "lv": {
        "unit": 99,
        "m": 15,
        "s1": 15,
        "s2": 15
      },
      "material_item_id": "JBEX_FIRE_UR"
    },
    {
      "iname": "JB_LW_VKTR_01_M",
      "lv": {
        "unit": 99,
        "m": 15,
        "s1": 15,
        "s2": 15
      },
      "material_item_id": "JBEX_WATER_UR"
    },
    {
      "iname": "JB_LW_SLEN_M",
      "lv": {
        "unit": 99,
        "m": 15,
        "s1": 15,
        "s2": 15
      },
      "material_item_id": "JBEX_SHINE_UR"
    },
    {
      "iname": "JB_LW_VERN_M",
      "lv": {
        "unit": 99,
        "m": 15,
        "s1": 15,
        "s2": 15
      },
      "material_item_id": "JBEX_THUN_UR"
    },
    {
      "iname": "JB_LW_STRN_01_M",
      "lv": {
        "unit": 99,
        "m": 15,
        "s1": 15,
        "s2": 15
      },
      "material_item_id": "JBEX_DARK_UR"
    },
    {
      "iname": "JB_LW_HLNA_M",
      "lv": {
        "unit": 99,
        "m": 15,
        "s1": 15,
        "s2": 15
      },
      "material_item_id": "JBEX_WIND_SSR"
    },
    {
      "iname": "JB_LW_GRSR_M",
      "lv": {
        "unit": 99,
        "m": 15,
        "s1": 15,
        "s2": 15
      },
      "material_item_id": "JBEX_WATER_UR"
    },
    {
      "iname": "JB_LW_CRIS_M",
      "lv": {
        "unit": 99,
        "m": 15,
        "s1": 15,
        "s2": 15
      },
      "material_item_id": "JBEX_WATER_SSR"
    },
    {
      "iname": "JB_LW_LVES_M",
      "lv": {
        "unit": 99,
        "m": 15,
        "s1": 15,
        "s2": 15
      },
      "material_item_id": "JBEX_THUN_SSR"
    },
    {
      "iname": "JB_LW_JEDN_M",
      "lv": {
        "unit": 99,
        "m": 15,
        "s1": 15,
        "s2": 15
      },
      "material_item_id": "JBEX_SHINE_UR"
    },
    {
      "iname": "JB_LW_VKTR_M",
      "lv": {
        "unit": 99,
        "m": 15,
        "s1": 15,
        "s2": 15
      },
      "material_item_id": "JBEX_ICE_UR"
    },
    {
      "iname": "JB_LW_RIRY_M",
      "lv": {
        "unit": 99,
        "m": 15,
        "s1": 15,
        "s2": 15
      },
      "material_item_id": "JBEX_DARK_SSR"
    },
    {
      "iname": "JB_LW_VLUC_M",
      "lv": {
        "unit": 99,
        "m": 15,
        "s1": 15,
        "s2": 15
      },
      "material_item_id": "JBEX_WIND_UR"
    }
  ]
}