{
  "info": {
    "angle_override": true,
    "angle": 314,
    "crystal_fade_enable": false,
    "crystal_fade_max": 0
  },
  "party": [
    {
      "name": "id:1",
      "x": 4,
      "y": 1,
      "dir": 1,
      "ct_calc": 0,
      "ct_val": 0,
      "brave": 0,
      "faith": 0,
      "fvoff": 0,
      "disphpg": 0,
      "disableact": 0,
      "disablemove": 0,
      "dmganm": 0,
      "block": 0,
      "ai": {
        "iname": "",
        "wait_e": 0,
        "search": 3,
        "sensing": 0
      },
      "chgTexSetting": {
        "hp_tbl": []
      },
      "entry_cond": {
        "timing": 0,
        "expr": "",
        "list": []
      },
      "wait_m": 0,
      "parent": "",
      "part": {
        "body": "",
        "id": "",
        "gauge": {
          "x": 0.0,
          "y": 0.0
        }
      }
    },
    {
      "name": "id:2",
      "x": 5,
      "y": 1,
      "dir": 1,
      "ct_calc": 0,
      "ct_val": 0,
      "brave": 0,
      "faith": 0,
      "fvoff": 0,
      "disphpg": 0,
      "disableact": 0,
      "disablemove": 0,
      "dmganm": 0,
      "block": 0,
      "ai": {
        "iname": "",
        "wait_e": 0,
        "search": 3,
        "sensing": 0
      },
      "chgTexSetting": {
        "hp_tbl": []
      },
      "entry_cond": {
        "timing": 0,
        "expr": "",
        "list": []
      },
      "wait_m": 0,
      "parent": "",
      "part": {
        "body": "",
        "id": "",
        "gauge": {
          "x": 0.0,
          "y": 0.0
        }
      }
    },
    {
      "name": "id:3",
      "x": 6,
      "y": 1,
      "dir": 1,
      "ct_calc": 0,
      "ct_val": 0,
      "brave": 0,
      "faith": 0,
      "fvoff": 0,
      "disphpg": 0,
      "disableact": 0,
      "disablemove": 0,
      "dmganm": 0,
      "block": 0,
      "ai": {
        "iname": "",
        "wait_e": 0,
        "search": 3,
        "sensing": 0
      },
      "chgTexSetting": {
        "hp_tbl": []
      },
      "entry_cond": {
        "timing": 0,
        "expr": "",
        "list": []
      },
      "wait_m": 0,
      "parent": "",
      "part": {
        "body": "",
        "id": "",
        "gauge": {
          "x": 0.0,
          "y": 0.0
        }
      }
    },
    {
      "name": "id:4",
      "x": 4,
      "y": 0,
      "dir": 1,
      "ct_calc": 0,
      "ct_val": 0,
      "brave": 0,
      "faith": 0,
      "fvoff": 0,
      "disphpg": 0,
      "disableact": 0,
      "disablemove": 0,
      "dmganm": 0,
      "block": 0,
      "ai": {
        "iname": "",
        "wait_e": 0,
        "search": 3,
        "sensing": 0
      },
      "chgTexSetting": {
        "hp_tbl": []
      },
      "entry_cond": {
        "timing": 0,
        "expr": "",
        "list": []
      },
      "wait_m": 0,
      "parent": "",
      "part": {
        "body": "",
        "id": "",
        "gauge": {
          "x": 0.0,
          "y": 0.0
        }
      }
    },
    {
      "name": "id:5",
      "x": 6,
      "y": 0,
      "dir": 1,
      "ct_calc": 0,
      "ct_val": 0,
      "brave": 0,
      "faith": 0,
      "fvoff": 0,
      "disphpg": 0,
      "disableact": 0,
      "disablemove": 0,
      "dmganm": 0,
      "block": 0,
      "ai": {
        "iname": "",
        "wait_e": 0,
        "search": 3,
        "sensing": 0
      },
      "chgTexSetting": {
        "hp_tbl": []
      },
      "entry_cond": {
        "timing": 0,
        "expr": "",
        "list": []
      },
      "wait_m": 0,
      "parent": "",
      "part": {
        "body": "",
        "id": "",
        "gauge": {
          "x": 0.0,
          "y": 0.0
        }
      }
    },
    {
      "name": "id:6",
      "x": 5,
      "y": 0,
      "dir": 1,
      "ct_calc": 0,
      "ct_val": 0,
      "brave": 0,
      "faith": 0,
      "fvoff": 0,
      "disphpg": 0,
      "disableact": 0,
      "disablemove": 0,
      "dmganm": 0,
      "block": 0,
      "ai": {
        "iname": "",
        "wait_e": 0,
        "search": 3,
        "sensing": 0
      },
      "chgTexSetting": {
        "hp_tbl": []
      },
      "entry_cond": {
        "timing": 0,
        "expr": "",
        "list": []
      },
      "wait_m": 0,
      "parent": "",
      "part": {
        "body": "",
        "id": "",
        "gauge": {
          "x": 0.0,
          "y": 0.0
        }
      }
    }
  ],
  "enemy": [
    {
      "name": "",
      "x": 5,
      "y": 8,
      "dir": 3,
      "ct_calc": 0,
      "ct_val": 0,
      "brave": 20,
      "faith": 0,
      "fvoff": 0,
      "disphpg": 0,
      "disableact": 0,
      "disablemove": 0,
      "dmganm": 0,
      "block": 0,
      "ai": {
        "iname": "AI_ENEMY_ATK_LV5",
        "wait_e": 0,
        "search": 15,
        "sensing": 0
      },
      "chgTexSetting": {
        "hp_tbl": []
      },
      "entry_cond": {
        "timing": 0,
        "expr": "",
        "list": []
      },
      "wait_m": 0,
      "parent": "",
      "part": {
        "body": "",
        "id": "",
        "gauge": {
          "x": 0.0,
          "y": 0.0
        }
      },
      "enemy_id": 2,
      "iname": "UN_LW_E_GLSP",
      "side": 1,
      "dead": 0,
      "lv": 50,
      "rare": 0,
      "awake": 6,
      "rank": 0,
      "elem": 6,
      "search": 0,
      "ctrl": 0,
      "nottar": 0,
      "fixdir": 0,
      "drop": "drop",
      "crystal": "CRYSTAL_00",
      "steal": "",
      "stealValue": 100,
      "nrmSkl": {
        "iname": "",
        "rank": 0,
        "rate": 0
      },
      "skills": [
        {
          "iname": "SK_GLSP_M_02",
          "rank": 10,
          "rate": 100
        }
      ],
      "fskl": "",
      "weight": 0,
      "tag": 0,
      "raid_type": 0,
      "dispOrder": 0,
      "pts": 0,
      "shield": false,
      "referenceGObjName": "",
      "status": "{\"list\":[{\"type\":1,\"value\":1355},{\"type\":4,\"value\":220},{\"type\":253,\"value\":-60},{\"type\":254,\"value\":0},{\"type\":2,\"value\":87},{\"type\":3,\"value\":98},{\"type\":250,\"value\":-20},{\"type\":307,\"value\":-50},{\"type\":504,\"value\":20},{\"type\":5,\"value\":10},{\"type\":9,\"value\":46},{\"type\":10,\"value\":169},{\"type\":151,\"value\":10},{\"type\":155,\"value\":-10}]}"
    },
    {
      "name": "",
      "x": 4,
      "y": 7,
      "dir": 3,
      "ct_calc": 0,
      "ct_val": 0,
      "brave": 20,
      "faith": 0,
      "fvoff": 0,
      "disphpg": 0,
      "disableact": 0,
      "disablemove": 0,
      "dmganm": 0,
      "block": 0,
      "ai": {
        "iname": "AI_ENEMY_ATK_LV5",
        "wait_e": 0,
        "search": 15,
        "sensing": 0
      },
      "chgTexSetting": {
        "hp_tbl": []
      },
      "entry_cond": {
        "timing": 0,
        "expr": "",
        "list": []
      },
      "wait_m": 0,
      "parent": "",
      "part": {
        "body": "",
        "id": "",
        "gauge": {
          "x": 0.0,
          "y": 0.0
        }
      },
      "enemy_id": 3,
      "iname": "UN_LW_E_GLSP",
      "side": 1,
      "dead": 0,
      "lv": 50,
      "rare": 0,
      "awake": 6,
      "rank": 0,
      "elem": 6,
      "search": 0,
      "ctrl": 0,
      "nottar": 0,
      "fixdir": 0,
      "drop": "drop",
      "crystal": "CRYSTAL_00",
      "steal": "",
      "stealValue": 100,
      "nrmSkl": {
        "iname": "",
        "rank": 0,
        "rate": 0
      },
      "skills": [
        {
          "iname": "SK_GLSP_M_02",
          "rank": 10,
          "rate": 100
        }
      ],
      "fskl": "",
      "weight": 0,
      "tag": 0,
      "raid_type": 0,
      "dispOrder": 0,
      "pts": 0,
      "shield": false,
      "referenceGObjName": "",
      "status": "{\"list\":[{\"type\":1,\"value\":1355},{\"type\":4,\"value\":220},{\"type\":253,\"value\":-60},{\"type\":254,\"value\":0},{\"type\":2,\"value\":87},{\"type\":3,\"value\":98},{\"type\":250,\"value\":-20},{\"type\":307,\"value\":-50},{\"type\":504,\"value\":20},{\"type\":5,\"value\":10},{\"type\":9,\"value\":46},{\"type\":10,\"value\":169},{\"type\":151,\"value\":10},{\"type\":155,\"value\":-10}]}"
    },
    {
      "name": "",
      "x": 3,
      "y": 8,
      "dir": 3,
      "ct_calc": 0,
      "ct_val": 0,
      "brave": 20,
      "faith": 0,
      "fvoff": 0,
      "disphpg": 0,
      "disableact": 0,
      "disablemove": 0,
      "dmganm": 0,
      "block": 0,
      "ai": {
        "iname": "AI_ENEMY_ATK_LV5",
        "wait_e": 0,
        "search": 15,
        "sensing": 0
      },
      "chgTexSetting": {
        "hp_tbl": []
      },
      "entry_cond": {
        "timing": 0,
        "expr": "",
        "list": []
      },
      "wait_m": 0,
      "parent": "",
      "part": {
        "body": "",
        "id": "",
        "gauge": {
          "x": 0.0,
          "y": 0.0
        }
      },
      "enemy_id": 4,
      "iname": "UN_LW_E_GLSP",
      "side": 1,
      "dead": 0,
      "lv": 50,
      "rare": 0,
      "awake": 6,
      "rank": 0,
      "elem": 6,
      "search": 0,
      "ctrl": 0,
      "nottar": 0,
      "fixdir": 0,
      "drop": "drop",
      "crystal": "CRYSTAL_00",
      "steal": "",
      "stealValue": 100,
      "nrmSkl": {
        "iname": "",
        "rank": 0,
        "rate": 0
      },
      "skills": [
        {
          "iname": "SK_GLSP_M_02",
          "rank": 10,
          "rate": 100
        }
      ],
      "fskl": "",
      "weight": 0,
      "tag": 0,
      "raid_type": 0,
      "dispOrder": 0,
      "pts": 0,
      "shield": false,
      "referenceGObjName": "",
      "status": "{\"list\":[{\"type\":1,\"value\":1355},{\"type\":4,\"value\":220},{\"type\":253,\"value\":-60},{\"type\":254,\"value\":0},{\"type\":2,\"value\":87},{\"type\":3,\"value\":98},{\"type\":250,\"value\":-20},{\"type\":307,\"value\":-50},{\"type\":504,\"value\":20},{\"type\":5,\"value\":10},{\"type\":9,\"value\":46},{\"type\":10,\"value\":169},{\"type\":151,\"value\":10},{\"type\":155,\"value\":-10}]}"
    },
    {
      "name": "",
      "x": 7,
      "y": 5,
      "dir": 3,
      "ct_calc": 0,
      "ct_val": 0,
      "brave": 25,
      "faith": 25,
      "fvoff": 0,
      "disphpg": 0,
      "disableact": 0,
      "disablemove": 0,
      "dmganm": 0,
      "block": 0,
      "ai": {
        "iname": "AI_ENEMY_ATK_LV5",
        "wait_e": 0,
        "search": 15,
        "sensing": 0
      },
      "chgTexSetting": {
        "hp_tbl": []
      },
      "entry_cond": {
        "timing": 0,
        "expr": "",
        "list": []
      },
      "wait_m": 0,
      "parent": "",
      "part": {
        "body": "",
        "id": "",
        "gauge": {
          "x": 0.0,
          "y": 0.0
        }
      },
      "enemy_id": 6,
      "iname": "UN_LW_E_CORL",
      "side": 1,
      "dead": 0,
      "lv": 50,
      "rare": 0,
      "awake": 6,
      "rank": 0,
      "elem": 5,
      "search": 0,
      "ctrl": 0,
      "nottar": 0,
      "fixdir": 0,
      "drop": "drop",
      "crystal": "CRYSTAL_00",
      "steal": "",
      "stealValue": 100,
      "nrmSkl": {
        "iname": "",
        "rank": 0,
        "rate": 0
      },
      "skills": [
        {
          "iname": "SK_CORL_M_01",
          "rank": 12,
          "rate": 100
        },
        {
          "iname": "SK_CORL_M_03",
          "rank": 12,
          "rate": 100
        }
      ],
      "fskl": "",
      "weight": 0,
      "tag": 0,
      "raid_type": 0,
      "dispOrder": 0,
      "pts": 0,
      "shield": false,
      "referenceGObjName": "",
      "status": "{\"list\":[{\"type\":1,\"value\":3558},{\"type\":4,\"value\":236},{\"type\":6,\"value\":236},{\"type\":5,\"value\":10},{\"type\":9,\"value\":50},{\"type\":504,\"value\":20},{\"type\":3,\"value\":100},{\"type\":8,\"value\":177},{\"type\":10,\"value\":177},{\"type\":7,\"value\":10},{\"type\":253,\"value\":0},{\"type\":250,\"value\":0},{\"type\":254,\"value\":0}]}"
    },
    {
      "name": "",
      "x": 1,
      "y": 8,
      "dir": 3,
      "ct_calc": 0,
      "ct_val": 0,
      "brave": 20,
      "faith": 15,
      "fvoff": 0,
      "disphpg": 0,
      "disableact": 0,
      "disablemove": 0,
      "dmganm": 0,
      "block": 0,
      "ai": {
        "iname": "AI_ENEMY_ATK_LV5",
        "wait_e": 0,
        "search": 15,
        "sensing": 0
      },
      "chgTexSetting": {
        "hp_tbl": []
      },
      "entry_cond": {
        "timing": 0,
        "expr": "",
        "list": []
      },
      "wait_m": 0,
      "parent": "",
      "part": {
        "body": "",
        "id": "",
        "gauge": {
          "x": 0.0,
          "y": 0.0
        }
      },
      "enemy_id": 5,
      "iname": "UN_LW_E_SKEL_02",
      "side": 1,
      "dead": 0,
      "lv": 50,
      "rare": 0,
      "awake": 6,
      "rank": 0,
      "elem": 8,
      "search": 0,
      "ctrl": 0,
      "nottar": 0,
      "fixdir": 0,
      "drop": "drop",
      "crystal": "CRYSTAL_00",
      "steal": "",
      "stealValue": 100,
      "nrmSkl": {
        "iname": "",
        "rank": 0,
        "rate": 0
      },
      "skills": [
        {
          "iname": "SK_SKEL_M_01",
          "rank": 10,
          "rate": 100
        },
        {
          "iname": "SK_SKEL_M_04",
          "rank": 10,
          "rate": 100
        }
      ],
      "fskl": "",
      "weight": 0,
      "tag": 0,
      "raid_type": 0,
      "dispOrder": 0,
      "pts": 0,
      "shield": false,
      "referenceGObjName": "",
      "status": "{\"list\":[{\"type\":1,\"value\":1663},{\"type\":254,\"value\":-15},{\"type\":3,\"value\":97},{\"type\":4,\"value\":244},{\"type\":9,\"value\":45},{\"type\":504,\"value\":20},{\"type\":251,\"value\":20},{\"type\":250,\"value\":10},{\"type\":157,\"value\":-10}]}"
    },
    {
      "name": "",
      "x": 1,
      "y": 3,
      "dir": 0,
      "ct_calc": 0,
      "ct_val": 200,
      "brave": 20,
      "faith": 0,
      "fvoff": 0,
      "disphpg": 0,
      "disableact": 0,
      "disablemove": 0,
      "dmganm": 0,
      "block": 0,
      "ai": {
        "iname": "AI_ENEMY_ATK_LV5",
        "wait_e": -1,
        "search": 15,
        "sensing": 0
      },
      "chgTexSetting": {
        "hp_tbl": []
      },
      "entry_cond": {
        "timing": 0,
        "expr": "",
        "list": [
          {
            "self": {
              "type": 19,
              "json": "{\"side\":1,\"count\":3}"
            },
            "childs": []
          }
        ]
      },
      "wait_m": 0,
      "parent": "",
      "part": {
        "body": "",
        "id": "",
        "gauge": {
          "x": 0.0,
          "y": 0.0
        }
      },
      "enemy_id": 7,
      "iname": "UN_LW_E_SO_02_HUN",
      "side": 1,
      "dead": 0,
      "lv": 50,
      "rare": 0,
      "awake": 6,
      "rank": 0,
      "elem": 2,
      "search": 0,
      "ctrl": 0,
      "nottar": 0,
      "fixdir": 0,
      "drop": "drop",
      "crystal": "CRYSTAL_00",
      "steal": "",
      "stealValue": 100,
      "nrmSkl": {
        "iname": "",
        "rank": 0,
        "rate": 0
      },
      "skills": [
        {
          "iname": "SK_LW_HUN_M_3",
          "rank": 10,
          "rate": 100
        },
        {
          "iname": "SK_LW_HUN_M_1",
          "rank": 10,
          "rate": 100
        },
        {
          "iname": "SK_BTL_RANGE_1-20_U",
          "rank": 2,
          "rate": 100
        },
        {
          "iname": "SK_BTL_STR_SHOT_1_100_U",
          "rank": 5,
          "rate": 100
        }
      ],
      "fskl": "",
      "weight": 0,
      "tag": 0,
      "raid_type": 0,
      "dispOrder": 0,
      "pts": 0,
      "shield": false,
      "referenceGObjName": "",
      "status": "{\"list\":[{\"type\":1,\"value\":855},{\"type\":4,\"value\":252},{\"type\":2,\"value\":87},{\"type\":3,\"value\":149},{\"type\":9,\"value\":60},{\"type\":8,\"value\":160},{\"type\":11,\"value\":3},{\"type\":406,\"value\":0},{\"type\":504,\"value\":20},{\"type\":409,\"value\":0},{\"type\":251,\"value\":-15},{\"type\":151,\"value\":-10},{\"type\":153,\"value\":10},{\"type\":250,\"value\":10},{\"type\":254,\"value\":-5}]}"
    },
    {
      "name": "",
      "x": 1,
      "y": 1,
      "dir": 0,
      "ct_calc": 0,
      "ct_val": 200,
      "brave": 20,
      "faith": 0,
      "fvoff": 0,
      "disphpg": 0,
      "disableact": 0,
      "disablemove": 0,
      "dmganm": 0,
      "block": 0,
      "ai": {
        "iname": "AI_ENEMY_ATK_LV5",
        "wait_e": -1,
        "search": 15,
        "sensing": 0
      },
      "chgTexSetting": {
        "hp_tbl": []
      },
      "entry_cond": {
        "timing": 0,
        "expr": "",
        "list": [
          {
            "self": {
              "type": 19,
              "json": "{\"side\":1,\"count\":3}"
            },
            "childs": []
          }
        ]
      },
      "wait_m": 0,
      "parent": "",
      "part": {
        "body": "",
        "id": "",
        "gauge": {
          "x": 0.0,
          "y": 0.0
        }
      },
      "enemy_id": 8,
      "iname": "UN_LW_E_SO_02_HUN",
      "side": 1,
      "dead": 0,
      "lv": 50,
      "rare": 0,
      "awake": 6,
      "rank": 0,
      "elem": 2,
      "search": 0,
      "ctrl": 0,
      "nottar": 0,
      "fixdir": 0,
      "drop": "drop",
      "crystal": "CRYSTAL_00",
      "steal": "",
      "stealValue": 100,
      "nrmSkl": {
        "iname": "",
        "rank": 0,
        "rate": 0
      },
      "skills": [
        {
          "iname": "SK_LW_HUN_M_3",
          "rank": 10,
          "rate": 100
        },
        {
          "iname": "SK_LW_HUN_M_1",
          "rank": 10,
          "rate": 100
        },
        {
          "iname": "SK_BTL_RANGE_1-20_U",
          "rank": 2,
          "rate": 100
        },
        {
          "iname": "SK_BTL_STR_SHOT_1_100_U",
          "rank": 5,
          "rate": 100
        }
      ],
      "fskl": "",
      "weight": 0,
      "tag": 0,
      "raid_type": 0,
      "dispOrder": 0,
      "pts": 0,
      "shield": false,
      "referenceGObjName": "",
      "status": "{\"list\":[{\"type\":1,\"value\":855},{\"type\":4,\"value\":252},{\"type\":2,\"value\":87},{\"type\":3,\"value\":149},{\"type\":9,\"value\":60},{\"type\":8,\"value\":160},{\"type\":11,\"value\":3},{\"type\":406,\"value\":0},{\"type\":504,\"value\":20},{\"type\":409,\"value\":0},{\"type\":251,\"value\":-15},{\"type\":151,\"value\":-10},{\"type\":153,\"value\":10},{\"type\":250,\"value\":10},{\"type\":254,\"value\":-5}]}"
    },
    {
      "name": "",
      "x": 1,
      "y": 2,
      "dir": 0,
      "ct_calc": 0,
      "ct_val": 200,
      "brave": 25,
      "faith": 0,
      "fvoff": 0,
      "disphpg": 0,
      "disableact": 0,
      "disablemove": 0,
      "dmganm": 0,
      "block": 0,
      "ai": {
        "iname": "AI_ENEMY_ATK_LV5",
        "wait_e": -1,
        "search": 15,
        "sensing": 0
      },
      "chgTexSetting": {
        "hp_tbl": []
      },
      "entry_cond": {
        "timing": 0,
        "expr": "",
        "list": [
          {
            "self": {
              "type": 19,
              "json": "{\"side\":1,\"count\":3}"
            },
            "childs": []
          }
        ]
      },
      "wait_m": 0,
      "parent": "",
      "part": {
        "body": "",
        "id": "",
        "gauge": {
          "x": 0.0,
          "y": 0.0
        }
      },
      "enemy_id": 9,
      "iname": "UN_LW_E_RRIR",
      "side": 1,
      "dead": 0,
      "lv": 50,
      "rare": 0,
      "awake": 6,
      "rank": 0,
      "elem": 3,
      "search": 0,
      "ctrl": 0,
      "nottar": 0,
      "fixdir": 0,
      "drop": "drop",
      "crystal": "CRYSTAL_00",
      "steal": "",
      "stealValue": 100,
      "nrmSkl": {
        "iname": "",
        "rank": 0,
        "rate": 0
      },
      "skills": [
        {
          "iname": "SK_LW_HUN_M_3",
          "rank": 10,
          "rate": 100
        },
        {
          "iname": "SK_LW_HUN_M_1",
          "rank": 10,
          "rate": 100
        },
        {
          "iname": "SK_BTL_RANGE_1-20_U",
          "rank": 2,
          "rate": 100
        },
        {
          "iname": "SK_BTL_STR_SHOT_1_100_U",
          "rank": 5,
          "rate": 100
        }
      ],
      "fskl": "",
      "weight": 0,
      "tag": 0,
      "raid_type": 0,
      "dispOrder": 0,
      "pts": 0,
      "shield": false,
      "referenceGObjName": "",
      "status": "{\"list\":[{\"type\":1,\"value\":1055},{\"type\":4,\"value\":288},{\"type\":2,\"value\":87},{\"type\":3,\"value\":210},{\"type\":9,\"value\":65},{\"type\":8,\"value\":210},{\"type\":11,\"value\":3},{\"type\":406,\"value\":0},{\"type\":409,\"value\":0},{\"type\":251,\"value\":-10},{\"type\":10,\"value\":145},{\"type\":6,\"value\":58}]}"
    }
  ],
  "arena": [],
  "wcond": {
    "timing": 0,
    "expr": "",
    "list": [
      {
        "self": {
          "type": 1,
          "json": "{\"side\":1,\"tag\":\"\"}"
        },
        "childs": []
      }
    ]
  },
  "lcond": {
    "timing": 0,
    "expr": "",
    "list": [
      {
        "self": {
          "type": 1,
          "json": "{\"side\":0,\"tag\":\"\"}"
        },
        "childs": []
      }
    ]
  },
  "gcond": [],
  "drop_table_list": [
    {
      "type": 1,
      "iname": "CRYSTAL_00",
      "num": 1,
      "drop_list": [
        {
          "drop_data": {
            "type": 99,
            "iname": "UN_GM_CRYSTAL",
            "num": 0,
            "secret": 0
          },
          "weight": 50
        },
        {
          "drop_data": {
            "type": 99,
            "iname": "UN_GM_CRYSTAL_01",
            "num": 1,
            "secret": 0
          },
          "weight": 50
        }
      ]
    },
    {
      "type": 0,
      "iname": "drop",
      "num": 1,
      "drop_list": [
        {
          "drop_data": {
            "type": 0,
            "iname": "IT_JB_MM_ALL_3",
            "num": 1,
            "secret": 0
          },
          "weight": 1250
        },
        {
          "drop_data": {
            "type": 0,
            "iname": "IT_JB_EM_SOIL_3",
            "num": 1,
            "secret": 0
          },
          "weight": 1250
        },
        {
          "drop_data": {
            "type": 0,
            "iname": "IT_JB_IM_ANGEL_3",
            "num": 1,
            "secret": 0
          },
          "weight": 250
        },
        {
          "drop_data": {
            "type": 0,
            "iname": "IT_UN_AW_SOIL",
            "num": 1,
            "secret": 0
          },
          "weight": 156
        },
        {
          "drop_data": {
            "type": 0,
            "iname": "IT_PI_COM_SOIL",
            "num": 1,
            "secret": 0
          },
          "weight": 78
        },
        {
          "drop_data": {
            "type": 0,
            "iname": "IT_PI_COM_ALL",
            "num": 1,
            "secret": 0
          },
          "weight": 2
        },
        {
          "drop_data": {
            "type": 0,
            "iname": "IT_AW_PIECE_SSR",
            "num": 1,
            "secret": 0
          },
          "weight": 2
        },
        {
          "drop_data": {
            "type": -1,
            "iname": "",
            "num": 0,
            "secret": 0
          },
          "weight": 7013
        }
      ]
    }
  ]
}